AnnSQL/AnnSQL.py
AnnSQL/BuildDb.py
AnnSQL/MakeDb.py
AnnSQL/__init__.py
AnnSQL-0.9.6.dist-info/LICENSE
AnnSQL-0.9.6.dist-info/METADATA
AnnSQL-0.9.6.dist-info/WHEEL
AnnSQL-0.9.6.dist-info/top_level.txt
AnnSQL-0.9.6.dist-info/RECORD
