Metadata-Version: 2.1
Name: AnnSQL
Version: 0.9.6
Summary: A Python SQL tool for converting Anndata objects to a relational DuckDb database. Methods are included for querying and basic single-cell preprocessing (experimental). 
Home-page: https://github.com/kennypavan/AnnSQL
Author: Kenny Pavan
Author-email: pavan@ohsu.edu
Classifier: Programming Language :: Python :: 3
Classifier: License :: OSI Approved :: MIT License
Classifier: Operating System :: OS Independent
Requires-Python: >=3.12
License-File: LICENSE
Requires-Dist: scanpy>=1.10.3
Requires-Dist: duckdb>=1.1.2
